setup.py
scalarTransportFlux/__init__.py
scalarTransportFlux.egg-info/PKG-INFO
scalarTransportFlux.egg-info/SOURCES.txt
scalarTransportFlux.egg-info/dependency_links.txt
scalarTransportFlux.egg-info/entry_points.txt
scalarTransportFlux.egg-info/requires.txt
scalarTransportFlux.egg-info/top_level.txt
scalarTransportFlux.egg-info/zip-safe
scalarTransportFlux/r1_6/__init__.py
scalarTransportFlux/r1_6_dev/__init__.py
scalarTransportFlux/r1_7_0/__init__.py
scalarTransportFlux/r2_0_0/__init__.py
scalarTransportFlux/r2_1_0/__init__.py